hijri_converter/__init__.py
hijri_converter/convert.py
hijri_converter/helpers.py
hijri_converter/locales.py
hijri_converter/py.typed
hijri_converter/ummalqura.py
hijri_converter-2.3.2.dist-info/licenses/LICENSE
hijri_converter-2.3.2.dist-info/METADATA
hijri_converter-2.3.2.dist-info/WHEEL
hijri_converter-2.3.2.dist-info/top_level.txt
hijri_converter-2.3.2.dist-info/RECORD
