Metadata-Version: 2.4
Name: hijri-converter
Version: 2.3.2
Summary: [DEPRECATED] Use 'hijridate' package instead
Author: Mohammed Alshehri
Author-email: 
License: MIT
Keywords: deprecated,hijri,gregorian,date,converter
Classifier: Development Status :: 7 - Inactive
Requires-Python: >=3.7
License-File: LICENSE
Requires-Dist: hijridate==2.3.0
Dynamic: description
Dynamic: description-content-type
Dynamic: license-file
